{
    "Player URL": "https://www.vlr.gg/player/14445/ac?timespan=all",
    "All Agents Stats": [
        {
            "Agent": "viper",
            "Usage": 20.0,
            "Rounds Played": "1020",
            "Rating": "1.03",
            "Average Combat Score": "204.7",
            "Kills:Death": "1.03",
            "Average Damage per Round": "128.3",
            "Kill, Assist, Survive, Trade %": "68%",
            "Kills Per Round": "0.71",
            "Assists Per Round": "0.28",
            "First Kills Per Round": "0.07",
            "First Deaths Per Round": "0.08",
            "Kills": "724",
            "Deaths": "703",
            "Assists": "288",
            "First Bloods": "68",
            "First Deaths": "70",
            "Rounds by Agents": 48
        },
        {
            "Agent": "skye",
            "Usage": 16.0,
            "Rounds Played": "788",
            "Rating": "1.01",
            "Average Combat Score": "186.1",
            "Kills:Death": "1.05",
            "Average Damage per Round": "114.7",
            "Kill, Assist, Survive, Trade %": "74%",
            "Kills Per Round": "0.70",
            "Assists Per Round": "0.27",
            "First Kills Per Round": "0.07",
            "First Deaths Per Round": "0.07",
            "Kills": "550",
            "Deaths": "523",
            "Assists": "211",
            "First Bloods": "56",
            "First Deaths": "55",
            "Rounds by Agents": 39
        },
        {
            "Agent": "chamber",
            "Usage": 13.0,
            "Rounds Played": "621",
            "Rating": "1.13",
            "Average Combat Score": "214.5",
            "Kills:Death": "1.25",
            "Average Damage per Round": "137.1",
            "Kill, Assist, Survive, Trade %": "72%",
            "Kills Per Round": "0.79",
            "Assists Per Round": "0.11",
            "First Kills Per Round": "0.16",
            "First Deaths Per Round": "0.11",
            "Kills": "488",
            "Deaths": "391",
            "Assists": "70",
            "First Bloods": "99",
            "First Deaths": "66",
            "Rounds by Agents": 31
        },
        {
            "Agent": "killjoy",
            "Usage": 12.0,
            "Rounds Played": "574",
            "Rating": "1.07",
            "Average Combat Score": "195.4",
            "Kills:Death": "1.13",
            "Average Damage per Round": "137.7",
            "Kill, Assist, Survive, Trade %": "72%",
            "Kills Per Round": "0.70",
            "Assists Per Round": "0.17",
            "First Kills Per Round": "0.07",
            "First Deaths Per Round": "0.07",
            "Kills": "403",
            "Deaths": "356",
            "Assists": "100",
            "First Bloods": "38",
            "First Deaths": "39",
            "Rounds by Agents": 29
        },
        {
            "Agent": "astra",
            "Usage": 10.0,
            "Rounds Played": "531",
            "Rating": "1.08",
            "Average Combat Score": "201.4",
            "Kills:Death": "1.07",
            "Average Damage per Round": "133.0",
            "Kill, Assist, Survive, Trade %": "72%",
            "Kills Per Round": "0.75",
            "Assists Per Round": "0.28",
            "First Kills Per Round": "0.06",
            "First Deaths Per Round": "0.06",
            "Kills": "396",
            "Deaths": "370",
            "Assists": "150",
            "First Bloods": "34",
            "First Deaths": "33",
            "Rounds by Agents": 25
        },
        {
            "Agent": "omen",
            "Usage": 10.0,
            "Rounds Played": "501",
            "Rating": "0.93",
            "Average Combat Score": "184.5",
            "Kills:Death": "0.92",
            "Average Damage per Round": "117.3",
            "Kill, Assist, Survive, Trade %": "67%",
            "Kills Per Round": "0.66",
            "Assists Per Round": "0.40",
            "First Kills Per Round": "0.04",
            "First Deaths Per Round": "0.08",
            "Kills": "329",
            "Deaths": "357",
            "Assists": "200",
            "First Bloods": "13",
            "First Deaths": "25",
            "Rounds by Agents": 24
        },
        {
            "Agent": "breach",
            "Usage": 9.0,
            "Rounds Played": "458",
            "Rating": "0.97",
            "Average Combat Score": "192.4",
            "Kills:Death": "0.89",
            "Average Damage per Round": "122.2",
            "Kill, Assist, Survive, Trade %": "72%",
            "Kills Per Round": "0.66",
            "Assists Per Round": "0.37",
            "First Kills Per Round": "0.04",
            "First Deaths Per Round": "0.06",
            "Kills": "302",
            "Deaths": "341",
            "Assists": "170",
            "First Bloods": "20",
            "First Deaths": "29",
            "Rounds by Agents": 23
        }
    ],
    "Current Team": "Titan Esports Club",
    "Player": "ac",
    "Signature Agents Ranked by Usage": [
        "viper",
        "skye",
        "chamber",
        "killjoy",
        "astra"
    ],
    "Total games played": 219,
    "Player stats": {
        "Rounds Played": "356",
        "Rating": "",
        "Average Combat Score": "197.8",
        "Kills:Death": "1.03",
        "Kill, Assist, Survive, Trade Percent": "",
        "Average Damage per Round": "128.1",
        "Kills Per Round": "0.71",
        "Assists Per Round": "0.35",
        "First Kills Per Round": "0.04",
        "First Deaths Per Round": "0.08",
        "Headshot Percent": "",
        "Clutch Success Percent%": "",
        "Clutches (won/played)": null,
        "Maximum Kills in a single map": null,
        "Kills": "252",
        "Deaths": "245",
        "Assists": "126",
        "First Kills": "9",
        "First Deaths": "17"
    }
}