{
    "Player URL": "https://www.vlr.gg/player/1711/khalil?timespan=all",
    "All Agents Stats": [
        {
            "Agent": "omen",
            "Usage": 34.0,
            "Rounds Played": "2074",
            "Rating": "1.00",
            "Average Combat Score": "187.7",
            "Kills:Death": "1.04",
            "Average Damage per Round": "119.6",
            "Kill, Assist, Survive, Trade %": "73%",
            "Kills Per Round": "0.68",
            "Assists Per Round": "0.29",
            "First Kills Per Round": "0.06",
            "First Deaths Per Round": "0.07",
            "Kills": "1403",
            "Deaths": "1344",
            "Assists": "608",
            "First Bloods": "132",
            "First Deaths": "139",
            "Rounds by Agents": 98
        },
        {
            "Agent": "killjoy",
            "Usage": 20.0,
            "Rounds Played": "1275",
            "Rating": "1.07",
            "Average Combat Score": "192.7",
            "Kills:Death": "1.12",
            "Average Damage per Round": "131.5",
            "Kill, Assist, Survive, Trade %": "73%",
            "Kills Per Round": "0.68",
            "Assists Per Round": "0.18",
            "First Kills Per Round": "0.07",
            "First Deaths Per Round": "0.06",
            "Kills": "867",
            "Deaths": "775",
            "Assists": "226",
            "First Bloods": "90",
            "First Deaths": "78",
            "Rounds by Agents": 59
        },
        {
            "Agent": "cypher",
            "Usage": 19.0,
            "Rounds Played": "1187",
            "Rating": "0.91",
            "Average Combat Score": "188.1",
            "Kills:Death": "1.02",
            "Average Damage per Round": "120.2",
            "Kill, Assist, Survive, Trade %": "69%",
            "Kills Per Round": "0.67",
            "Assists Per Round": "0.24",
            "First Kills Per Round": "0.08",
            "First Deaths Per Round": "0.06",
            "Kills": "793",
            "Deaths": "778",
            "Assists": "281",
            "First Bloods": "93",
            "First Deaths": "69",
            "Rounds by Agents": 56
        },
        {
            "Agent": "viper",
            "Usage": 9.0,
            "Rounds Played": "561",
            "Rating": "1.04",
            "Average Combat Score": "191.6",
            "Kills:Death": "1.02",
            "Average Damage per Round": "128.6",
            "Kill, Assist, Survive, Trade %": "72%",
            "Kills Per Round": "0.67",
            "Assists Per Round": "0.29",
            "First Kills Per Round": "0.06",
            "First Deaths Per Round": "0.05",
            "Kills": "377",
            "Deaths": "370",
            "Assists": "160",
            "First Bloods": "34",
            "First Deaths": "27",
            "Rounds by Agents": 27
        },
        {
            "Agent": "brimstone",
            "Usage": 7.0,
            "Rounds Played": "445",
            "Rating": "1.08",
            "Average Combat Score": "201.1",
            "Kills:Death": "1.10",
            "Average Damage per Round": "129.7",
            "Kill, Assist, Survive, Trade %": "79%",
            "Kills Per Round": "0.71",
            "Assists Per Round": "0.43",
            "First Kills Per Round": "0.05",
            "First Deaths Per Round": "0.05",
            "Kills": "318",
            "Deaths": "288",
            "Assists": "193",
            "First Bloods": "21",
            "First Deaths": "23",
            "Rounds by Agents": 21
        },
        {
            "Agent": "astra",
            "Usage": 6.0,
            "Rounds Played": "385",
            "Rating": "0.95",
            "Average Combat Score": "169.9",
            "Kills:Death": "0.97",
            "Average Damage per Round": "107.9",
            "Kill, Assist, Survive, Trade %": "74%",
            "Kills Per Round": "0.61",
            "Assists Per Round": "0.30",
            "First Kills Per Round": "0.04",
            "First Deaths Per Round": "0.04",
            "Kills": "235",
            "Deaths": "243",
            "Assists": "116",
            "First Bloods": "16",
            "First Deaths": "15",
            "Rounds by Agents": 18
        }
    ],
    "Current Team": "FURIA",
    "Player": "khalil",
    "Signature Agents Ranked by Usage": [
        "omen",
        "killjoy",
        "cypher",
        "viper",
        "brimstone"
    ],
    "Total games played": 279,
    "Player stats": {
        "Rounds Played": "512",
        "Rating": "0.93",
        "Average Combat Score": "173.8",
        "Kills:Death": "0.88",
        "Kill, Assist, Survive, Trade Percent": "70%",
        "Average Damage per Round": "119.1",
        "Kills Per Round": "0.63",
        "Assists Per Round": "0.25",
        "First Kills Per Round": "0.05",
        "First Deaths Per Round": "0.08",
        "Headshot Percent": "30%",
        "Clutch Success Percent%": "18%",
        "Clutches (won/played)": null,
        "Maximum Kills in a single map": null,
        "Kills": "320",
        "Deaths": "362",
        "Assists": "130",
        "First Kills": "26",
        "First Deaths": "39"
    }
}