{
    "Player URL": "https://www.vlr.gg/player/22831/art?timespan=all",
    "All Agents Stats": [
        {
            "Agent": "omen",
            "Usage": 45.0,
            "Rounds Played": "492",
            "Rating": "1.08",
            "Average Combat Score": "187.3",
            "Kills:Death": "1.07",
            "Average Damage per Round": "123.3",
            "Kill, Assist, Survive, Trade %": "76%",
            "Kills Per Round": "0.66",
            "Assists Per Round": "0.42",
            "First Kills Per Round": "0.04",
            "First Deaths Per Round": "0.04",
            "Kills": "326",
            "Deaths": "304",
            "Assists": "209",
            "First Bloods": "20",
            "First Deaths": "20",
            "Rounds by Agents": 22
        },
        {
            "Agent": "brimstone",
            "Usage": 10.0,
            "Rounds Played": "115",
            "Rating": "1.08",
            "Average Combat Score": "205.2",
            "Kills:Death": "1.03",
            "Average Damage per Round": "128.7",
            "Kill, Assist, Survive, Trade %": "78%",
            "Kills Per Round": "0.70",
            "Assists Per Round": "0.40",
            "First Kills Per Round": "0.08",
            "First Deaths Per Round": "0.06",
            "Kills": "81",
            "Deaths": "79",
            "Assists": "46",
            "First Bloods": "9",
            "First Deaths": "7",
            "Rounds by Agents": 5
        },
        {
            "Agent": "sage",
            "Usage": 8.0,
            "Rounds Played": "78",
            "Rating": "0.96",
            "Average Combat Score": "199.3",
            "Kills:Death": "0.85",
            "Average Damage per Round": "133.4",
            "Kill, Assist, Survive, Trade %": "73%",
            "Kills Per Round": "0.65",
            "Assists Per Round": "0.36",
            "First Kills Per Round": "0.09",
            "First Deaths Per Round": "0.08",
            "Kills": "51",
            "Deaths": "60",
            "Assists": "28",
            "First Bloods": "7",
            "First Deaths": "6",
            "Rounds by Agents": 4
        },
        {
            "Agent": "cypher",
            "Usage": 6.0,
            "Rounds Played": "64",
            "Rating": "0.90",
            "Average Combat Score": "158.7",
            "Kills:Death": "0.92",
            "Average Damage per Round": "105.5",
            "Kill, Assist, Survive, Trade %": "67%",
            "Kills Per Round": "0.56",
            "Assists Per Round": "0.13",
            "First Kills Per Round": "0.08",
            "First Deaths Per Round": "0.06",
            "Kills": "36",
            "Deaths": "39",
            "Assists": "8",
            "First Bloods": "5",
            "First Deaths": "4",
            "Rounds by Agents": 3
        },
        {
            "Agent": "astra",
            "Usage": 6.0,
            "Rounds Played": "60",
            "Rating": "0.92",
            "Average Combat Score": "197.0",
            "Kills:Death": "0.91",
            "Average Damage per Round": "127.7",
            "Kill, Assist, Survive, Trade %": "62%",
            "Kills Per Round": "0.70",
            "Assists Per Round": "0.25",
            "First Kills Per Round": "0.08",
            "First Deaths Per Round": "0.08",
            "Kills": "42",
            "Deaths": "46",
            "Assists": "15",
            "First Bloods": "5",
            "First Deaths": "5",
            "Rounds by Agents": 3
        },
        {
            "Agent": "kayo",
            "Usage": 6.0,
            "Rounds Played": "54",
            "Rating": "0.77",
            "Average Combat Score": "133.3",
            "Kills:Death": "0.60",
            "Average Damage per Round": "93.0",
            "Kill, Assist, Survive, Trade %": "59%",
            "Kills Per Round": "0.48",
            "Assists Per Round": "0.37",
            "First Kills Per Round": "0.07",
            "First Deaths Per Round": "0.07",
            "Kills": "26",
            "Deaths": "43",
            "Assists": "20",
            "First Bloods": "4",
            "First Deaths": "4",
            "Rounds by Agents": 3
        }
    ],
    "Current Team": "Koopa Troopas",
    "Player": "art",
    "Signature Agents Ranked by Usage": [
        "omen",
        "brimstone",
        "sage",
        "cypher",
        "astra"
    ],
    "Total games played": 40,
    "Player stats": {
        "Rounds Played": "202",
        "Rating": "1.08",
        "Average Combat Score": "182.5",
        "Kills:Death": "1.12",
        "Kill, Assist, Survive, Trade Percent": "79%",
        "Average Damage per Round": "121.2",
        "Kills Per Round": "0.66",
        "Assists Per Round": "0.39",
        "First Kills Per Round": "0.03",
        "First Deaths Per Round": "0.03",
        "Headshot Percent": "28%",
        "Clutch Success Percent%": "11%",
        "Clutches (won/played)": null,
        "Maximum Kills in a single map": null,
        "Kills": "133",
        "Deaths": "119",
        "Assists": "79",
        "First Kills": "7",
        "First Deaths": "7"
    }
}