{
    "Player URL": "https://www.vlr.gg/player/6731/merjie?timespan=all",
    "All Agents Stats": [
        {
            "Agent": "jett",
            "Usage": 25.0,
            "Rounds Played": "471",
            "Rating": "0.95",
            "Average Combat Score": "210.7",
            "Kills:Death": "0.90",
            "Average Damage per Round": "129.7",
            "Kill, Assist, Survive, Trade %": "65%",
            "Kills Per Round": "0.71",
            "Assists Per Round": "0.16",
            "First Kills Per Round": "0.15",
            "First Deaths Per Round": "0.17",
            "Kills": "335",
            "Deaths": "372",
            "Assists": "74",
            "First Bloods": "72",
            "First Deaths": "80",
            "Rounds by Agents": 23
        },
        {
            "Agent": "raze",
            "Usage": 15.0,
            "Rounds Played": "267",
            "Rating": "0.91",
            "Average Combat Score": "222.2",
            "Kills:Death": "0.90",
            "Average Damage per Round": "142.1",
            "Kill, Assist, Survive, Trade %": "71%",
            "Kills Per Round": "0.73",
            "Assists Per Round": "0.22",
            "First Kills Per Round": "0.12",
            "First Deaths Per Round": "0.17",
            "Kills": "195",
            "Deaths": "216",
            "Assists": "60",
            "First Bloods": "33",
            "First Deaths": "45",
            "Rounds by Agents": 14
        },
        {
            "Agent": "kayo",
            "Usage": 14.0,
            "Rounds Played": "259",
            "Rating": "1.11",
            "Average Combat Score": "206.7",
            "Kills:Death": "1.02",
            "Average Damage per Round": "140.6",
            "Kill, Assist, Survive, Trade %": "77%",
            "Kills Per Round": "0.73",
            "Assists Per Round": "0.49",
            "First Kills Per Round": "0.10",
            "First Deaths Per Round": "0.09",
            "Kills": "188",
            "Deaths": "184",
            "Assists": "127",
            "First Bloods": "26",
            "First Deaths": "24",
            "Rounds by Agents": 13
        },
        {
            "Agent": "skye",
            "Usage": 9.0,
            "Rounds Played": "171",
            "Rating": "0.94",
            "Average Combat Score": "192.1",
            "Kills:Death": "0.90",
            "Average Damage per Round": "128.8",
            "Kill, Assist, Survive, Trade %": "68%",
            "Kills Per Round": "0.65",
            "Assists Per Round": "0.35",
            "First Kills Per Round": "0.08",
            "First Deaths Per Round": "0.09",
            "Kills": "112",
            "Deaths": "124",
            "Assists": "59",
            "First Bloods": "14",
            "First Deaths": "15",
            "Rounds by Agents": 8
        },
        {
            "Agent": "omen",
            "Usage": 9.0,
            "Rounds Played": "166",
            "Rating": "0.98",
            "Average Combat Score": "169.6",
            "Kills:Death": "0.90",
            "Average Damage per Round": "112.2",
            "Kill, Assist, Survive, Trade %": "73%",
            "Kills Per Round": "0.61",
            "Assists Per Round": "0.48",
            "First Kills Per Round": "0.05",
            "First Deaths Per Round": "0.10",
            "Kills": "102",
            "Deaths": "113",
            "Assists": "79",
            "First Bloods": "9",
            "First Deaths": "17",
            "Rounds by Agents": 8
        },
        {
            "Agent": "astra",
            "Usage": 7.0,
            "Rounds Played": "129",
            "Rating": "0.97",
            "Average Combat Score": "185.8",
            "Kills:Death": "0.90",
            "Average Damage per Round": "118.7",
            "Kill, Assist, Survive, Trade %": "69%",
            "Kills Per Round": "0.64",
            "Assists Per Round": "0.37",
            "First Kills Per Round": "0.03",
            "First Deaths Per Round": "0.10",
            "Kills": "83",
            "Deaths": "92",
            "Assists": "48",
            "First Bloods": "4",
            "First Deaths": "13",
            "Rounds by Agents": 6
        }
    ],
    "Current Team": "Unknown",
    "Player": "merjie",
    "Signature Agents Ranked by Usage": [
        "jett",
        "raze",
        "kayo",
        "skye",
        "omen"
    ],
    "Total games played": 72,
    "Player stats": {
        "Rounds Played": "248",
        "Rating": "0.85",
        "Average Combat Score": "170.3",
        "Kills:Death": "0.78",
        "Kill, Assist, Survive, Trade Percent": "68%",
        "Average Damage per Round": "110.4",
        "Kills Per Round": "0.58",
        "Assists Per Round": "0.36",
        "First Kills Per Round": "0.07",
        "First Deaths Per Round": "0.08",
        "Headshot Percent": "25%",
        "Clutch Success Percent%": "11%",
        "Clutches (won/played)": null,
        "Maximum Kills in a single map": null,
        "Kills": "144",
        "Deaths": "185",
        "Assists": "90",
        "First Kills": "18",
        "First Deaths": "19"
    }
}