{
    "Player URL": "https://www.vlr.gg/player/11242/blu?timespan=all",
    "All Agents Stats": [
        {
            "Agent": "killjoy",
            "Usage": 19.0,
            "Rounds Played": "1449",
            "Rating": "0.96",
            "Average Combat Score": "193.4",
            "Kills:Death": "0.98",
            "Average Damage per Round": "126.6",
            "Kill, Assist, Survive, Trade %": "70%",
            "Kills Per Round": "0.67",
            "Assists Per Round": "0.20",
            "First Kills Per Round": "0.09",
            "First Deaths Per Round": "0.10",
            "Kills": "974",
            "Deaths": "993",
            "Assists": "288",
            "First Bloods": "137",
            "First Deaths": "147",
            "Rounds by Agents": 71
        },
        {
            "Agent": "skye",
            "Usage": 15.0,
            "Rounds Played": "1100",
            "Rating": "0.83",
            "Average Combat Score": "159.3",
            "Kills:Death": "0.78",
            "Average Damage per Round": "104.2",
            "Kill, Assist, Survive, Trade %": "67%",
            "Kills Per Round": "0.55",
            "Assists Per Round": "0.39",
            "First Kills Per Round": "0.07",
            "First Deaths Per Round": "0.10",
            "Kills": "607",
            "Deaths": "783",
            "Assists": "424",
            "First Bloods": "77",
            "First Deaths": "112",
            "Rounds by Agents": 55
        },
        {
            "Agent": "cypher",
            "Usage": 12.0,
            "Rounds Played": "926",
            "Rating": "0.78",
            "Average Combat Score": "174.0",
            "Kills:Death": "0.84",
            "Average Damage per Round": "118.2",
            "Kill, Assist, Survive, Trade %": "64%",
            "Kills Per Round": "0.63",
            "Assists Per Round": "0.21",
            "First Kills Per Round": "0.08",
            "First Deaths Per Round": "0.12",
            "Kills": "580",
            "Deaths": "693",
            "Assists": "190",
            "First Bloods": "75",
            "First Deaths": "110",
            "Rounds by Agents": 45
        },
        {
            "Agent": "sage",
            "Usage": 12.0,
            "Rounds Played": "850",
            "Rating": "0.90",
            "Average Combat Score": "186.3",
            "Kills:Death": "0.91",
            "Average Damage per Round": "119.1",
            "Kill, Assist, Survive, Trade %": "67%",
            "Kills Per Round": "0.64",
            "Assists Per Round": "0.35",
            "First Kills Per Round": "0.09",
            "First Deaths Per Round": "0.11",
            "Kills": "545",
            "Deaths": "598",
            "Assists": "297",
            "First Bloods": "76",
            "First Deaths": "94",
            "Rounds by Agents": 43
        },
        {
            "Agent": "gekko",
            "Usage": 8.0,
            "Rounds Played": "607",
            "Rating": "0.97",
            "Average Combat Score": "170.9",
            "Kills:Death": "1.02",
            "Average Damage per Round": "113.6",
            "Kill, Assist, Survive, Trade %": "74%",
            "Kills Per Round": "0.62",
            "Assists Per Round": "0.32",
            "First Kills Per Round": "0.06",
            "First Deaths Per Round": "0.09",
            "Kills": "376",
            "Deaths": "369",
            "Assists": "195",
            "First Bloods": "39",
            "First Deaths": "55",
            "Rounds by Agents": 30
        },
        {
            "Agent": "fade",
            "Usage": 7.0,
            "Rounds Played": "492",
            "Rating": "1.01",
            "Average Combat Score": "182.9",
            "Kills:Death": "1.03",
            "Average Damage per Round": "119.3",
            "Kill, Assist, Survive, Trade %": "75%",
            "Kills Per Round": "0.65",
            "Assists Per Round": "0.34",
            "First Kills Per Round": "0.07",
            "First Deaths Per Round": "0.07",
            "Kills": "322",
            "Deaths": "312",
            "Assists": "166",
            "First Bloods": "33",
            "First Deaths": "33",
            "Rounds by Agents": 26
        },
        {
            "Agent": "kayo",
            "Usage": 7.0,
            "Rounds Played": "492",
            "Rating": "0.91",
            "Average Combat Score": "176.7",
            "Kills:Death": "0.83",
            "Average Damage per Round": "115.9",
            "Kill, Assist, Survive, Trade %": "73%",
            "Kills Per Round": "0.60",
            "Assists Per Round": "0.52",
            "First Kills Per Round": "0.08",
            "First Deaths Per Round": "0.09",
            "Kills": "295",
            "Deaths": "357",
            "Assists": "257",
            "First Bloods": "38",
            "First Deaths": "45",
            "Rounds by Agents": 26
        },
        {
            "Agent": "viper",
            "Usage": 6.0,
            "Rounds Played": "457",
            "Rating": "0.79",
            "Average Combat Score": "179.1",
            "Kills:Death": "0.81",
            "Average Damage per Round": "117.5",
            "Kill, Assist, Survive, Trade %": "65%",
            "Kills Per Round": "0.61",
            "Assists Per Round": "0.26",
            "First Kills Per Round": "0.09",
            "First Deaths Per Round": "0.15",
            "Kills": "278",
            "Deaths": "342",
            "Assists": "117",
            "First Bloods": "41",
            "First Deaths": "67",
            "Rounds by Agents": 22
        },
        {
            "Agent": "sova",
            "Usage": 5.0,
            "Rounds Played": "397",
            "Rating": "0.93",
            "Average Combat Score": "185.8",
            "Kills:Death": "0.90",
            "Average Damage per Round": "124.4",
            "Kill, Assist, Survive, Trade %": "68%",
            "Kills Per Round": "0.62",
            "Assists Per Round": "0.24",
            "First Kills Per Round": "0.07",
            "First Deaths Per Round": "0.08",
            "Kills": "248",
            "Deaths": "277",
            "Assists": "94",
            "First Bloods": "29",
            "First Deaths": "32",
            "Rounds by Agents": 19
        }
    ],
    "Current Team": "LOUD GC",
    "Player": "blu",
    "Signature Agents Ranked by Usage": [
        "killjoy",
        "skye",
        "cypher",
        "sage",
        "gekko"
    ],
    "Total games played": 337,
    "Player stats": {
        "Rounds Played": "549",
        "Rating": "0.81",
        "Average Combat Score": "146.5",
        "Kills:Death": "0.76",
        "Kill, Assist, Survive, Trade Percent": "67%",
        "Average Damage per Round": "97.6",
        "Kills Per Round": "0.52",
        "Assists Per Round": "0.33",
        "First Kills Per Round": "0.07",
        "First Deaths Per Round": "0.10",
        "Headshot Percent": "29%",
        "Clutch Success Percent%": "18%",
        "Clutches (won/played)": null,
        "Maximum Kills in a single map": null,
        "Kills": "285",
        "Deaths": "373",
        "Assists": "179",
        "First Kills": "37",
        "First Deaths": "56"
    }
}