{
    "Player URL": "https://www.vlr.gg/player/19556/melya?timespan=all",
    "All Agents Stats": [
        {
            "Agent": "omen",
            "Usage": 22.0,
            "Rounds Played": "1339",
            "Rating": "1.17",
            "Average Combat Score": "207.8",
            "Kills:Death": "1.21",
            "Average Damage per Round": "133.3",
            "Kill, Assist, Survive, Trade %": "76%",
            "Kills Per Round": "0.76",
            "Assists Per Round": "0.42",
            "First Kills Per Round": "0.06",
            "First Deaths Per Round": "0.05",
            "Kills": "1024",
            "Deaths": "843",
            "Assists": "561",
            "First Bloods": "76",
            "First Deaths": "63",
            "Rounds by Agents": 65
        },
        {
            "Agent": "viper",
            "Usage": 9.0,
            "Rounds Played": "490",
            "Rating": "0.98",
            "Average Combat Score": "205.1",
            "Kills:Death": "0.99",
            "Average Damage per Round": "136.5",
            "Kill, Assist, Survive, Trade %": "71%",
            "Kills Per Round": "0.71",
            "Assists Per Round": "0.27",
            "First Kills Per Round": "0.07",
            "First Deaths Per Round": "0.08",
            "Kills": "348",
            "Deaths": "350",
            "Assists": "131",
            "First Bloods": "32",
            "First Deaths": "40",
            "Rounds by Agents": 25
        },
        {
            "Agent": "raze",
            "Usage": 8.0,
            "Rounds Played": "446",
            "Rating": "1.11",
            "Average Combat Score": "262.4",
            "Kills:Death": "1.20",
            "Average Damage per Round": "172.5",
            "Kill, Assist, Survive, Trade %": "71%",
            "Kills Per Round": "0.87",
            "Assists Per Round": "0.24",
            "First Kills Per Round": "0.14",
            "First Deaths Per Round": "0.15",
            "Kills": "390",
            "Deaths": "326",
            "Assists": "108",
            "First Bloods": "62",
            "First Deaths": "66",
            "Rounds by Agents": 23
        },
        {
            "Agent": "killjoy",
            "Usage": 7.0,
            "Rounds Played": "411",
            "Rating": "0.99",
            "Average Combat Score": "202.2",
            "Kills:Death": "1.05",
            "Average Damage per Round": "137.6",
            "Kill, Assist, Survive, Trade %": "68%",
            "Kills Per Round": "0.73",
            "Assists Per Round": "0.15",
            "First Kills Per Round": "0.09",
            "First Deaths Per Round": "0.09",
            "Kills": "300",
            "Deaths": "286",
            "Assists": "63",
            "First Bloods": "38",
            "First Deaths": "38",
            "Rounds by Agents": 21
        },
        {
            "Agent": "kayo",
            "Usage": 6.0,
            "Rounds Played": "386",
            "Rating": "1.08",
            "Average Combat Score": "206.9",
            "Kills:Death": "1.03",
            "Average Damage per Round": "139.2",
            "Kill, Assist, Survive, Trade %": "73%",
            "Kills Per Round": "0.74",
            "Assists Per Round": "0.49",
            "First Kills Per Round": "0.06",
            "First Deaths Per Round": "0.08",
            "Kills": "284",
            "Deaths": "277",
            "Assists": "191",
            "First Bloods": "22",
            "First Deaths": "29",
            "Rounds by Agents": 18
        },
        {
            "Agent": "skye",
            "Usage": 6.0,
            "Rounds Played": "379",
            "Rating": "1.19",
            "Average Combat Score": "240.1",
            "Kills:Death": "1.20",
            "Average Damage per Round": "149.1",
            "Kill, Assist, Survive, Trade %": "75%",
            "Kills Per Round": "0.85",
            "Assists Per Round": "0.45",
            "First Kills Per Round": "0.06",
            "First Deaths Per Round": "0.05",
            "Kills": "321",
            "Deaths": "267",
            "Assists": "172",
            "First Bloods": "24",
            "First Deaths": "20",
            "Rounds by Agents": 18
        },
        {
            "Agent": "clove",
            "Usage": 6.0,
            "Rounds Played": "341",
            "Rating": "1.17",
            "Average Combat Score": "264.4",
            "Kills:Death": "1.16",
            "Average Damage per Round": "176.5",
            "Kill, Assist, Survive, Trade %": "82%",
            "Kills Per Round": "0.94",
            "Assists Per Round": "0.32",
            "First Kills Per Round": "0.09",
            "First Deaths Per Round": "0.06",
            "Kills": "322",
            "Deaths": "277",
            "Assists": "110",
            "First Bloods": "32",
            "First Deaths": "19",
            "Rounds by Agents": 17
        },
        {
            "Agent": "sova",
            "Usage": 6.0,
            "Rounds Played": "327",
            "Rating": "1.00",
            "Average Combat Score": "201.7",
            "Kills:Death": "0.90",
            "Average Damage per Round": "142.3",
            "Kill, Assist, Survive, Trade %": "71%",
            "Kills Per Round": "0.68",
            "Assists Per Round": "0.31",
            "First Kills Per Round": "0.08",
            "First Deaths Per Round": "0.07",
            "Kills": "221",
            "Deaths": "246",
            "Assists": "101",
            "First Bloods": "25",
            "First Deaths": "22",
            "Rounds by Agents": 17
        },
        {
            "Agent": "jett",
            "Usage": 5.0,
            "Rounds Played": "268",
            "Rating": "1.04",
            "Average Combat Score": "217.7",
            "Kills:Death": "1.09",
            "Average Damage per Round": "145.4",
            "Kill, Assist, Survive, Trade %": "68%",
            "Kills Per Round": "0.79",
            "Assists Per Round": "0.14",
            "First Kills Per Round": "0.17",
            "First Deaths Per Round": "0.17",
            "Kills": "212",
            "Deaths": "195",
            "Assists": "37",
            "First Bloods": "46",
            "First Deaths": "46",
            "Rounds by Agents": 15
        }
    ],
    "Current Team": "Elation Esports",
    "Player": "melya",
    "Signature Agents Ranked by Usage": [
        "omen",
        "viper",
        "raze",
        "killjoy",
        "kayo"
    ],
    "Total games played": 219,
    "Player stats": {
        "Rounds Played": "535",
        "Rating": "1.04",
        "Average Combat Score": "219.0",
        "Kills:Death": "1.00",
        "Kill, Assist, Survive, Trade Percent": "72%",
        "Average Damage per Round": "146.5",
        "Kills Per Round": "0.75",
        "Assists Per Round": "0.36",
        "First Kills Per Round": "0.07",
        "First Deaths Per Round": "0.08",
        "Headshot Percent": "26%",
        "Clutch Success Percent%": "14%",
        "Clutches (won/played)": null,
        "Maximum Kills in a single map": null,
        "Kills": "400",
        "Deaths": "402",
        "Assists": "191",
        "First Kills": "37",
        "First Deaths": "44"
    }
}