{
    "Player URL": "https://www.vlr.gg/player/25858/sw?timespan=all",
    "All Agents Stats": [
        {
            "Agent": "viper",
            "Usage": 35.0,
            "Rounds Played": "1756",
            "Rating": "1.03",
            "Average Combat Score": "208.1",
            "Kills:Death": "1.03",
            "Average Damage per Round": "136.9",
            "Kill, Assist, Survive, Trade %": "73%",
            "Kills Per Round": "0.70",
            "Assists Per Round": "0.32",
            "First Kills Per Round": "0.09",
            "First Deaths Per Round": "0.10",
            "Kills": "1236",
            "Deaths": "1197",
            "Assists": "562",
            "First Bloods": "162",
            "First Deaths": "178",
            "Rounds by Agents": 83
        },
        {
            "Agent": "omen",
            "Usage": 29.0,
            "Rounds Played": "1444",
            "Rating": "1.06",
            "Average Combat Score": "201.9",
            "Kills:Death": "1.05",
            "Average Damage per Round": "130.7",
            "Kill, Assist, Survive, Trade %": "73%",
            "Kills Per Round": "0.71",
            "Assists Per Round": "0.41",
            "First Kills Per Round": "0.10",
            "First Deaths Per Round": "0.08",
            "Kills": "1029",
            "Deaths": "980",
            "Assists": "593",
            "First Bloods": "139",
            "First Deaths": "112",
            "Rounds by Agents": 69
        },
        {
            "Agent": "astra",
            "Usage": 18.0,
            "Rounds Played": "891",
            "Rating": "1.00",
            "Average Combat Score": "193.8",
            "Kills:Death": "1.00",
            "Average Damage per Round": "126.8",
            "Kill, Assist, Survive, Trade %": "73%",
            "Kills Per Round": "0.68",
            "Assists Per Round": "0.34",
            "First Kills Per Round": "0.08",
            "First Deaths Per Round": "0.09",
            "Kills": "603",
            "Deaths": "606",
            "Assists": "301",
            "First Bloods": "75",
            "First Deaths": "84",
            "Rounds by Agents": 43
        },
        {
            "Agent": "brimstone",
            "Usage": 15.0,
            "Rounds Played": "755",
            "Rating": "0.97",
            "Average Combat Score": "190.0",
            "Kills:Death": "0.93",
            "Average Damage per Round": "123.3",
            "Kill, Assist, Survive, Trade %": "75%",
            "Kills Per Round": "0.65",
            "Assists Per Round": "0.40",
            "First Kills Per Round": "0.07",
            "First Deaths Per Round": "0.08",
            "Kills": "488",
            "Deaths": "522",
            "Assists": "303",
            "First Bloods": "52",
            "First Deaths": "60",
            "Rounds by Agents": 35
        }
    ],
    "Current Team": "DELIRA",
    "Player": "sw",
    "Signature Agents Ranked by Usage": [
        "viper",
        "omen",
        "astra",
        "brimstone"
    ],
    "Total games played": 230,
    "Player stats": {
        "Rounds Played": "544",
        "Rating": "0.93",
        "Average Combat Score": "174.4",
        "Kills:Death": "0.87",
        "Kill, Assist, Survive, Trade Percent": "75%",
        "Average Damage per Round": "117.0",
        "Kills Per Round": "0.58",
        "Assists Per Round": "0.39",
        "First Kills Per Round": "0.07",
        "First Deaths Per Round": "0.11",
        "Headshot Percent": "22%",
        "Clutch Success Percent%": "20%",
        "Clutches (won/played)": null,
        "Maximum Kills in a single map": null,
        "Kills": "316",
        "Deaths": "365",
        "Assists": "213",
        "First Kills": "36",
        "First Deaths": "59"
    }
}